gtdb_validation_tk/VERSION
gtdb_validation_tk/__init__.py
gtdb_validation_tk/__main__.py
gtdb_validation_tk/check_species_names.py
gtdb_validation_tk/check_taxa.py
gtdb_validation_tk/check_taxonomy_file.py
gtdb_validation_tk/common.py
gtdb_validation_tk/main.py
gtdb_validation_tk/merge_genera.py
gtdb_validation_tk/missing_genera.py
gtdb_validation_tk/red_check.py
gtdb_validation_tk/red_diff.py
gtdb_validation_tk/spellchecker.py
gtdb_validation_tk/suffix_table.py
gtdb_validation_tk/tax_diff.py
gtdb_validation_tk/taxon_utils.py
gtdb_validation_tk/tree_diff.py
gtdb_validation_tk/validate_gtdb_clusters_by_name.py
gtdb_validation_tk/validate_species_by_ncbi_name.py
gtdb_validation_tk/validate_species_clusters.py
gtdb_validation_tk/validate_type_material.py
gtdb_validation_tk/visualisation.py
gtdb_validation_tk-0.1.17.dist-info/LICENSE
gtdb_validation_tk-0.1.17.dist-info/METADATA
gtdb_validation_tk-0.1.17.dist-info/WHEEL
gtdb_validation_tk-0.1.17.dist-info/entry_points.txt
gtdb_validation_tk-0.1.17.dist-info/top_level.txt
gtdb_validation_tk-0.1.17.dist-info/RECORD
