Metadata-Version: 2.1
Name: gtdb-validation-tk
Version: 0.1.17
Summary: A toolbox for validating the GTDB taxonomy.
Home-page: https://pypi.org/project/gtdb-validation-tk/
Author: Donovan Parks
Author-email: donovan.parks@gmail.com
License: GPL3
Platform: UNKNOWN
Classifier: Intended Audience :: Science/Research
Classifier: License :: OSI Approved :: GNU General Public License v3 (GPLv3)
Classifier: Natural Language :: English
Classifier: Programming Language :: Python :: 3
Classifier: Programming Language :: Python :: 3.6
Classifier: Programming Language :: Python :: 3.7
Classifier: Programming Language :: Python :: 3.8
Classifier: Topic :: Scientific/Engineering :: Bio-Informatics
License-File: LICENSE
Requires-Dist: numpy (>=1.8.0)
Requires-Dist: biolib (>=0.1.8)
Requires-Dist: dendropy (>=4.0.0)
Requires-Dist: fuzzywuzzy
